serpost/__init__.py
serpost/cli.py
serpost/serpost.py
serpost-0.2.0.dist-info/METADATA
serpost-0.2.0.dist-info/RECORD
serpost-0.2.0.dist-info/WHEEL
serpost-0.2.0.dist-info/entry_points.txt
serpost-0.2.0.dist-info/top_level.txt
tests/__init__.py
