Metadata-Version: 2.1
Name: serpost
Version: 0.2.0
Summary: CLI tool for search tracking number in SERPOST page
Home-page: https://github.com/erickgnavar/serpost/
Author: Erick Navarro
Author-email: erick@navarro.io
License: MIT License
Keywords: tracking serpost
Platform: UNKNOWN
Classifier: Development Status :: 4 - Beta
Classifier: Environment :: Console
Classifier: Intended Audience :: End Users/Desktop
Classifier: License :: OSI Approved :: MIT License
Classifier: Operating System :: OS Independent
Classifier: Programming Language :: Python
Classifier: Programming Language :: Python :: 2.7
Classifier: Programming Language :: Python :: 3
Classifier: Programming Language :: Python :: 3.4
Classifier: Programming Language :: Python :: 3.5
Classifier: Topic :: Utilities
Requires-Dist: beautifulsoup4
Requires-Dist: lxml
